kafka_connect/__init__.py
kafka_connect/__main__.py
kafka_connect/kafka_connect.py
kafka_connect_cli-0.2.5.dist-info/METADATA
kafka_connect_cli-0.2.5.dist-info/WHEEL
kafka_connect_cli-0.2.5.dist-info/dependency_links.txt
kafka_connect_cli-0.2.5.dist-info/entry_points.txt
kafka_connect_cli-0.2.5.dist-info/top_level.txt
kafka_connect_cli-0.2.5.dist-info/RECORD
