Metadata-Version: 2.1
Name: kafka-connect-cli
Version: 0.2.5
Summary: A Simple CLI for Kafka connect REST API
Home-page: https://github.com/andrew00x/kafka-connect-cli
Download-URL: https://github.com/andrew00x/kafka-connect-cli/archive/refs/tags/0.2.5.tar.gz
Author: Andrii Parfonov
Author-email: andrew00x@gmail.com
License: MIT
Platform: UNKNOWN
Requires-Python: >=3.6
Requires-Dist: requests (==2.27.1)
Requires-Dist: urllib3 (==1.26.9)
Requires-Dist: twine
Requires-Dist: wheel
